strnn/__init__.py
strnn/factorizers/__init__.py
strnn/factorizers/factorizer.py
strnn/factorizers/greedy.py
strnn/factorizers/made.py
strnn/factorizers/zuko.py
strnn/models/__init__.py
strnn/models/causal_arflow.py
strnn/models/config_constants.py
strnn/models/model_utils.py
strnn/models/normalizing_flow.py
strnn/models/strNN.py
strnn/models/strNNDensityEstimator.py
strnn/models/continuous_flows/__init__.py
strnn/models/continuous_flows/continuous_flow.py
strnn/models/continuous_flows/odenets.py
strnn/models/continuous_flows/ffjord/__init__.py
strnn/models/continuous_flows/ffjord/cnf.py
strnn/models/continuous_flows/ffjord/container.py
strnn/models/continuous_flows/ffjord/odefunc.py
strnn/models/discrete_flows/__init__.py
strnn/models/discrete_flows/autoregressive_flow.py
strnn/models/discrete_flows/conditioners/__init__.py
strnn/models/discrete_flows/conditioners/conditioner.py
strnn/models/discrete_flows/conditioners/gnf_conditioner.py
strnn/models/discrete_flows/conditioners/made_conditioner.py
strnn/models/discrete_flows/conditioners/straf_conditioner.py
strnn/models/discrete_flows/normalizers/__init__.py
strnn/models/discrete_flows/normalizers/affine_normalizer.py
strnn/models/discrete_flows/normalizers/normalizer.py
strnn/models/discrete_flows/normalizers/umnn_normalizer.py
strnn-0.2.0.dist-info/LICENSE
strnn-0.2.0.dist-info/METADATA
strnn-0.2.0.dist-info/WHEEL
strnn-0.2.0.dist-info/top_level.txt
strnn-0.2.0.dist-info/RECORD
