Metadata-Version: 2.1
Name: strnn
Version: 0.2.0
Summary: PyTorch package for Structured Neural Networks.
Home-page: https://github.com/rgklab/StructuredNNs
Author: RGKLab
Classifier: Programming Language :: Python :: 3
Classifier: License :: OSI Approved :: MIT License
Requires-Python: >=3.11
License-File: LICENSE
Requires-Dist: torch >=2.0.0
Requires-Dist: scikit-learn
Requires-Dist: matplotlib
Requires-Dist: torchdiffeq ==0.2.3
Requires-Dist: UMNN
Requires-Dist: wandb
